setup.py
html_to_text/__init__.py
html_to_text/parser.py
html_to_text.egg-info/PKG-INFO
html_to_text.egg-info/SOURCES.txt
html_to_text.egg-info/dependency_links.txt
html_to_text.egg-info/top_level.txt