Metadata-Version: 1.0
Name: html-to-text
Version: 1.0.0
Summary: Simple library for extracting text from html documents.
Home-page: https://github.com/emludei/html_to_text
Author: emludei
Author-email: incontrol64@yandex.ru
License: Apache License 2.0
Platform: UNKNOWN
